libsvmdata/__init__.py
libsvmdata/datasets.py
libsvmdata-0.4.1.dist-info/LICENSE
libsvmdata-0.4.1.dist-info/METADATA
libsvmdata-0.4.1.dist-info/WHEEL
libsvmdata-0.4.1.dist-info/top_level.txt
libsvmdata-0.4.1.dist-info/RECORD
