Metadata-Version: 2.1
Name: libsvmdata
Version: 0.4.1
Summary: Fetcher for LIBSVM datasets
Download-URL: https://github.com/mathurinm/libsvmdata.git
Maintainer: Mathurin Massias
Maintainer-email: mathurin.massias@gmail.com
License: BSD (3-clause)
License-File: LICENSE
Requires-Dist: download
Requires-Dist: numpy (>=1.12)
Requires-Dist: scikit-learn
Requires-Dist: scipy
